{
  "greeting": "亲爱的",
  "name": "卫思夷",
  "greetingText": "早上好呀！",
  "wishText": "桃气茶茶",
  "imagePath": "img/lydia2.png",
  "text1": "2024年4月，你陪我在郑州看了人生中的第一场演唱会；春天在沈阳，你笑靥如花；夏天的北京，你陪我疯狂。",
  "textInChatBox": "生日快乐宝贝！",
  "sendButtonLabel": "发送",
  "text2": "9月在昆山，我记得你坐在我后座抱着我，晚风吹过你的粉色长发，路遇孔雀开屏的机车男，那是永不磨灭的青春。",
  "text3": "我们一次次走向彼此：冬天和春天在北京重逢，春天你又来昆山看我，夏天我们再次在北京相见。",
  "text4": "7月在长春，你陪我走过难过的时候。4月在烟台，我们一起在海边做个小孩。",
  "text4Adjective": "原来我们已经一起走了这么远。",
  "text5Entry": "希望你继续",
  "text5Content": "勇敢、自由、热烈、真诚",
  "smiley": ":)",
  "bigTextPart1": "很高兴",
  "bigTextPart2": "认识你",
  "wishHeading": "生日快乐！",
  "outroText": "怎么样，喜欢吗",
  "replayText": "如果你想再看一遍，就再点击一次好啦",
  "outroSmiley": ":)"
}
